glibs_excel-1.0.0-py3.10-nspkg.pth
glibs/excel.py
glibs_excel-1.0.0.dist-info/LICENSE
glibs_excel-1.0.0.dist-info/METADATA
glibs_excel-1.0.0.dist-info/WHEEL
glibs_excel-1.0.0.dist-info/namespace_packages.txt
glibs_excel-1.0.0.dist-info/top_level.txt
glibs_excel-1.0.0.dist-info/RECORD
